backend/__init__.py
backend/app.py
backend/chunk_handler.py
backend/config.py
backend/encryption.py
devshare-1.0.0.dist-info/METADATA
devshare-1.0.0.dist-info/WHEEL
devshare-1.0.0.dist-info/entry_points.txt
devshare-1.0.0.dist-info/top_level.txt
devshare-1.0.0.dist-info/RECORD
